<?xml version="1.0" encoding="utf-8" ?><dwsync><file name="modal-inc.html" server="Macintosh HD/Applications/MAMP/htdocs/" local="3527092116" remote="3527092116" Dst="-1" /><file name="modal-inc.html" server="198.238.33.26/psp_web_update/" local="3529026616" remote="3529026401" Dst="-1" /><file name="footer-inc.html" server="198.238.33.26/psp_web_update/" local="3529078665" remote="3529078451" Dst="-1" /><file name="board_contact.html" server="Macintosh HD/Applications/MAMP/htdocs/" local="3488224916" remote="3488224916" Dst="-1" /><file name="boards_eb_links.html" server="Macintosh HD/Applications/MAMP/htdocs/" local="3524576464" remote="3524576464" Dst="-1" /><file name="boards_lc_links.html" server="Macintosh HD/Applications/MAMP/htdocs/" local="3502717082" remote="3502717082" Dst="-1" /><file name="boards_sp_links.html" server="Macintosh HD/Applications/MAMP/htdocs/" local="3502667295" remote="3502667295" Dst="-1" /><file name="footer-inc.html" server="Macintosh HD/Applications/MAMP/htdocs/" local="3527093658" remote="3527093658" Dst="-1" /><file name="board_contact.html" server="198.238.33.26/psp_web_update/" local="3488224916" remote="3527194835" Dst="-1" /><file name="boards_eb_links.html" server="198.238.33.26/psp_web_update/" local="3524576464" remote="3527194835" Dst="-1" /><file name="boards_lc_links.html" server="198.238.33.26/psp_web_update/" local="3502717082" remote="3527194835" Dst="-1" /><file name="boards_sp_links.html" server="198.238.33.26/psp_web_update/" local="3502667295" remote="3527194835" Dst="-1" /><file name="ln-local-recovery-efforts.html" server="198.238.33.26/psp_web_update/" local="3529007157" remote="3529006939" Dst="-1" /><file name="ln-psp-overview.html" server="198.238.33.26/psp_web_update/" local="3528373105" remote="3528372876" Dst="-1" /><file name="media_contact.html" server="198.238.33.26/psp_web_update/" local="3529003268" remote="3529003050" Dst="-1" /><file name="ln-sos.html" server="198.238.33.26/psp_web_update/" local="3528942888" remote="3528987986" Dst="-1" /><file name="ln-NEP.html" server="198.238.33.26/psp_web_update/" local="3529076475" remote="3529076260" Dst="-1" /><file name="ln-2016-AA.html" server="198.238.33.26/psp_web_update/" local="3529015657" remote="3529015441" Dst="-1" /><file name="ln-salmon.html" server="198.238.33.26/psp_web_update/" local="3528576482" remote="3528576258" Dst="-1" /><file name="ln-science-basis.html" server="198.238.33.26/psp_web_update/" local="3528572171" remote="3528571947" Dst="-1" /><file name="ln-eval-actions.html" server="198.238.33.26/psp_web_update/" local="3529078673" remote="3529078457" Dst="-1" /><file name="ln-boards.html" server="198.238.33.26/psp_web_update/" local="3528723218" remote="3528723187" Dst="-1" /><file name="gov-delivery-inc.html" server="198.238.33.26/psp_web_update/" local="3529004736" remote="3529004520" Dst="-1" /><file name="ln-gov.html" server="198.238.33.26/psp_web_update/" local="3529017363" remote="3529017146" Dst="-1" /></dwsync>