<?xml version="1.0" encoding="utf-8" ?><dwsync><file name="sos.php" server="Macintosh HD/Applications/MAMP/htdocs/" local="3527194365" remote="3527194365" Dst="-1" /><file name="sos.php" server="198.238.33.26/psp_web_update/" local="3528387816" remote="3528390147" Dst="-1" /><file name="evaluating-actions-to-recover-puget-sound.php" server="198.238.33.26/psp_web_update/" local="3528582928" remote="3528582704" Dst="-1" /><file name="evaluating-health-of-puget-sound.php" server="198.238.33.26/psp_web_update/" local="3528582228" remote="3528582004" Dst="-1" /><file name="LC_about.php" server="198.238.33.26/psp_web_update/" local="3528645049" remote="3528645147" Dst="-1" /><file name="LC_meetings.php" server="198.238.33.26/psp_web_update/" local="3528578729" remote="3528578505" Dst="-1" /><file name="partnership-boards-overview.php" server="198.238.33.26/psp_web_update/" local="3528645296" remote="3528645148" Dst="-1" /><file name="puget-sound-recovery.php" server="198.238.33.26/psp_web_update/" local="3528644925" remote="3528645145" Dst="-1" /><file name="science-and-evaluation-overview.php" server="198.238.33.26/psp_web_update/" local="3528572108" remote="3528575345" Dst="-1" /><file name="science-basis-of-recovery-overview.php" server="198.238.33.26/psp_web_update/" local="3528572144" remote="3528575345" Dst="-1" /><file name="staff.php" server="198.238.33.26/psp_web_update/" local="3528575818" remote="3528575594" Dst="-1" /><file name="staff.php" server="Macintosh HD/Applications/MAMP/htdocs/" local="3527194365" remote="3527194365" Dst="-1" /><file name="LC_about.php" server="Macintosh HD/Applications/MAMP/htdocs/" local="3527194365" remote="3527194365" Dst="-1" /><file name="evaluating-actions-to-recover-puget-sound.php" server="Macintosh HD/Applications/MAMP/htdocs/" local="3527267215" remote="3527267215" Dst="-1" /><file name="evaluating-health-of-puget-sound.php" server="Macintosh HD/Applications/MAMP/htdocs/" local="3527194365" remote="3527194365" Dst="-1" /><file name="LC_meetings.php" server="Macintosh HD/Applications/MAMP/htdocs/" local="3527194365" remote="3527194365" Dst="-1" /><file name="partnership-boards-overview.php" server="Macintosh HD/Applications/MAMP/htdocs/" local="3527197745" remote="3527197745" Dst="-1" /><file name="puget-sound-recovery.php" server="Macintosh HD/Applications/MAMP/htdocs/" local="3527194365" remote="3527194365" Dst="-1" /><file name="science-and-evaluation-overview.php" server="Macintosh HD/Applications/MAMP/htdocs/" local="3527194365" remote="3527194365" Dst="-1" /><file name="science-basis-of-recovery-overview.php" server="Macintosh HD/Applications/MAMP/htdocs/" local="3527194365" remote="3527194365" Dst="-1" /><file name="SP_meetings.php" server="198.238.33.26/psp_web_update/" local="3528645076" remote="3528645147" Dst="-1" /><file name="SP_about.php" server="198.238.33.26/psp_web_update/" local="3528645064" remote="3528645147" Dst="-1" /><file name="EB_about.php" server="198.238.33.26/psp_web_update/" local="3528645009" remote="3528645146" Dst="-1" /><file name="EB_meetings.php" server="198.238.33.26/psp_web_update/" local="3528645022" remote="3528645146" Dst="-1" /><file name="SR_about.php" server="198.238.33.26/psp_web_update/" local="3528645104" remote="3528645147" Dst="-1" /><file name="SR_meetings.php" server="198.238.33.26/psp_web_update/" local="3528645116" remote="3528645148" Dst="-1" /><file name="NEP-overview.php" server="Macintosh HD/Applications/MAMP/htdocs/" local="3527360948" remote="3527360948" Dst="-1" /><file name="NEP-overview.php" server="198.238.33.26/psp_web_update/" local="3528572649" remote="3528575352" Dst="-1" /><file name="NEP-health-of-puget-sound.php" server="198.238.33.26/psp_web_update/" local="3528576239" remote="3528576015" Dst="-1" /><file name="NEP-puget-sound-estuary.php" server="198.238.33.26/psp_web_update/" local="3528576151" remote="3528575928" Dst="-1" /><file name="ecosystem-status.php" server="198.238.33.26/psp_web_update/" local="3528222498" remote="3528248561" Dst="-1" /><file name="sos-resources.php" server="198.238.33.26/psp_web_update/" local="3528387985" remote="3528387758" Dst="-1" /><file name="NEP-regional-approach.php" server="198.238.33.26/psp_web_update/" local="3528575993" remote="3528575769" Dst="-1" /><file name="NEP-communications-toolkit.php" server="198.238.33.26/psp_web_update/" local="3528576262" remote="3528576038" Dst="-1" /><file name="NEP-solicitation-and-grants.php" server="198.238.33.26/psp_web_update/" local="3528576200" remote="3528575976" Dst="-1" /><file name="NEP-funding.php" server="198.238.33.26/psp_web_update/" local="3528576252" remote="3528576028" Dst="-1" /><file name="NEP-local.php" server="198.238.33.26/psp_web_update/" local="3528572638" remote="3528575352" Dst="-1" /><file name="PSAR.php" server="198.238.33.26/psp_web_update/" local="3528577520" remote="3528577297" Dst="-1" /><file name="salmon-lead-entities.php" server="198.238.33.26/psp_web_update/" local="3528571910" remote="3528575348" Dst="-1" /><file name="salmon-recovery-overview.php" server="198.238.33.26/psp_web_update/" local="3528582400" remote="3528582176" Dst="-1" /><file name="salmon-recovery-status.php" server="198.238.33.26/psp_web_update/" local="3528581761" remote="3528581537" Dst="-1" /><file name="salmon-resources.php" server="198.238.33.26/psp_web_update/" local="3528571948" remote="3528575347" Dst="-1" /><file name="salmon-three-year-work-plans.php" server="198.238.33.26/psp_web_update/" local="3528571977" remote="3528575346" Dst="-1" /><file name="salmon-watershed-recovery-plans.php" server="198.238.33.26/psp_web_update/" local="3528572072" remote="3528575346" Dst="-1" /><file name="index.php" server="198.238.33.26/psp_web_update/" local="3528580593" remote="3528580408" Dst="-1" /><file name="LIO-overview.php" server="198.238.33.26/psp_web_update/" local="3528577494" remote="3528577270" Dst="-1" /><file name="LIO-2-year-plan.php" server="198.238.33.26/psp_web_update/" local="3528577435" remote="3528577211" Dst="-1" /><file name="LIO-5-year-plan.php" server="198.238.33.26/psp_web_update/" local="3528577443" remote="3528577218" Dst="-1" /><file name="funding-programs.php" server="198.238.33.26/psp_web_update/" local="3528574909" remote="3528575326" Dst="-1" /><file name="action_agenda_strategic_initiatives.php" server="198.238.33.26/psp_web_update/" local="3528574556" remote="3528575318" Dst="-1" /><file name="2014_action_agenda_download.php" server="198.238.33.26/psp_web_update/" local="3528574158" remote="3528575320" Dst="-1" /><file name="action_agenda_center.php" server="198.238.33.26/psp_web_update/" local="3528574532" remote="3528575319" Dst="-1" /><file name="2016_AA_NTA.php" server="198.238.33.26/psp_web_update/" local="3528574450" remote="3528575320" Dst="-1" /><file name="2016_AA_SITT.php" server="198.238.33.26/psp_web_update/" local="3528574484" remote="3528575319" Dst="-1" /><file name="2016_AA_LIO_planning.php" server="198.238.33.26/psp_web_update/" local="3528574270" remote="3528575320" Dst="-1" /><file name="2016_AA_announcements.php" server="198.238.33.26/psp_web_update/" local="3528574214" remote="3528575320" Dst="-1" /><file name="2016_AA_who_is_involved.php" server="198.238.33.26/psp_web_update/" local="3528574510" remote="3528575319" Dst="-1" /><file name="2016_AA_update.php" server="198.238.33.26/psp_web_update/" local="3528574498" remote="3528575319" Dst="-1" /><file name="2016_AA_implementation_strategies.php" server="198.238.33.26/psp_web_update/" local="3528576426" remote="3528576201" Dst="-1" /><file name="evaluating-effective-action.php" server="198.238.33.26/psp_web_update/" local="3528575517" remote="3528575294" Dst="-1" /><file name="evaluating-human-wellbeing.php" server="198.238.33.26/psp_web_update/" local="3528582209" remote="3528581990" Dst="-1" /><file name="evaluating-PSEMP.php" server="198.238.33.26/psp_web_update/" local="3528582041" remote="3528581997" Dst="-1" /><file name="evaluating-about-sos.php" server="198.238.33.26/psp_web_update/" local="3528574765" remote="3528575308" Dst="-1" /><file name="evaluating-agency-performance-management.php" server="198.238.33.26/psp_web_update/" local="3528577639" remote="3528577416" Dst="-1" /><file name="evaluating-public-opinion.php" server="198.238.33.26/psp_web_update/" local="3528574883" remote="3528575306" Dst="-1" /><file name="evaluating-about-project-atlas.php" server="198.238.33.26/psp_web_update/" local="3528574733" remote="3528575309" Dst="-1" /><file name="evaluating-about-report-card.php" server="198.238.33.26/psp_web_update/" local="3528574745" remote="3528575308" Dst="-1" /><file name="evaluating-vital-signs.php" server="198.238.33.26/psp_web_update/" local="3528577692" remote="3528577469" Dst="-1" /><file name="oilspills.php" server="198.238.33.26/psp_web_update/" local="3528574941" remote="3528575350" Dst="-1" /><file name="press.php" server="198.238.33.26/psp_web_update/" local="3528575798" remote="3528575574" Dst="-1" /><file name="employment.php" server="198.238.33.26/psp_web_update/" local="3528574702" remote="3528575309" Dst="-1" /><file name="programs.php" server="198.238.33.26/psp_web_update/" local="3528575808" remote="3528575584" Dst="-1" /><file name="contact.php" server="198.238.33.26/psp_web_update/" local="3528575851" remote="3528575627" Dst="-1" /><file name="econet.php" server="198.238.33.26/psp_web_update/" local="3528577427" remote="3528577203" Dst="-1" /><file name="sheida-sahandy-bio.php" server="198.238.33.26/psp_web_update/" local="3528572290" remote="3528572066" Dst="-1" /><file name="evaluating-about-NEP-atlas.php" server="198.238.33.26/psp_web_update/" local="3528574715" remote="3528575309" Dst="-1" /><file name="social-strategies-overview.php" server="198.238.33.26/psp_web_update/" local="3528647922" remote="3528647699" Dst="-1" /><file name="science-open-standards.php" server="198.238.33.26/psp_web_update/" local="3528572242" remote="3528575345" Dst="-1" /><file name="science-puget-sound-pressures-assessment.php" server="198.238.33.26/psp_web_update/" local="3528572263" remote="3528575345" Dst="-1" /><file name="lessons-learned.php" server="198.238.33.26/psp_web_update/" local="3528222498" remote="3528248567" Dst="-1" /><file name="science-adaptive-management-framework.php" server="198.238.33.26/psp_web_update/" local="3528578581" remote="3528578356" Dst="-1" /><file name="science-based-decision-making.php" server="198.238.33.26/psp_web_update/" local="3528572131" remote="3528575345" Dst="-1" /><file name="science-biennial-science-workplan.php" server="198.238.33.26/psp_web_update/" local="3528572200" remote="3528571977" Dst="-1" /><file name="science-strategic-science-plan.php" server="198.238.33.26/psp_web_update/" local="3528572277" remote="3528575344" Dst="-1" /><file name="puget-sound-partnership.php" server="198.238.33.26/psp_web_update/" local="3528575787" remote="3528575563" Dst="-1" /><file name="aa-progress.php" server="198.238.33.26/psp_web_update/" local="3528387880" remote="3528387656" Dst="-1" /><file name="definitions.php" server="198.238.33.26/psp_web_update/" local="3528387913" remote="3528387687" Dst="-1" /><file name="ecosystem-recovery-progress.php" server="198.238.33.26/psp_web_update/" local="3528387946" remote="3528387721" Dst="-1" /><file name="legislative_updates.php" server="198.238.33.26/psp_web_update/" local="3528572501" remote="3528575354" Dst="-1" /><file name="funding.php" server="198.238.33.26/psp_web_update/" local="3528574925" remote="3528575326" Dst="-1" /><file name="econet_PSSH.php" server="198.238.33.26/psp_web_update/" local="3528574651" remote="3528575310" Dst="-1" /><file name="econet_PSSH_webwidgets.html" server="198.238.33.26/psp_web_update/" local="3528569901" remote="3528570097" Dst="-1" /><file name="redirect list.rtf" server="198.238.33.26/psp_web_update/" local="3528473253" remote="3528575348" Dst="-1" /></dwsync>